github_webhook_app/__init__.py
github_webhook_app/__setup__.py
github_webhook_app/abc_service.py
github_webhook_app/models/__init__.py
github_webhook_app-1.1.1.dist-info/LICENSE
github_webhook_app-1.1.1.dist-info/METADATA
github_webhook_app-1.1.1.dist-info/WHEEL
github_webhook_app-1.1.1.dist-info/RECORD
